{
  "openapi": "3.0.1",
  "info": {
    "title": "BiblioPlomb API",
    "description": "API Bibliothèque BiblioPlomb",
    "version": "v1"
  },
  "paths": {
    "/api/RoleApi": {
      "post": {
        "tags": [
          "RoleApi"
        ],
        "requestBody": {
          "content": {
            "application/json": {
              "schema": {
                "type": "string"
              }
            },
            "text/json": {
              "schema": {
                "type": "string"
              }
            },
            "application/*+json": {
              "schema": {
                "type": "string"
              }
            }
          }
        },
        "responses": {
          "200": {
            "description": "OK"
          }
        }
      },
      "get": {
        "tags": [
          "RoleApi"
        ],
        "responses": {
          "200": {
            "description": "OK"
          }
        }
      }
    },
    "/api/RoleApi/type/{type}": {
      "get": {
        "tags": [
          "RoleApi"
        ],
        "parameters": [
          {
            "name": "type",
            "in": "path",
            "required": true,
            "schema": {
              "type": "string"
            }
          }
        ],
        "responses": {
          "200": {
            "description": "OK"
          }
        }
      }
    },
    "/api/RoleApi/id/{id}": {
      "get": {
        "tags": [
          "RoleApi"
        ],
        "parameters": [
          {
            "name": "id",
            "in": "path",
            "required": true,
            "schema": {
              "type": "integer",
              "format": "int32"
            }
          }
        ],
        "responses": {
          "200": {
            "description": "OK"
          }
        }
      }
    },
    "/api/RoleApi/search": {
      "get": {
        "tags": [
          "RoleApi"
        ],
        "parameters": [
          {
            "name": "query",
            "in": "query",
            "schema": {
              "type": "string"
            }
          }
        ],
        "responses": {
          "200": {
            "description": "OK"
          }
        }
      }
    },
    "/api/RoleApi/{id}": {
      "put": {
        "tags": [
          "RoleApi"
        ],
        "parameters": [
          {
            "name": "id",
            "in": "path",
            "required": true,
            "schema": {
              "type": "integer",
              "format": "int32"
            }
          }
        ],
        "requestBody": {
          "content": {
            "application/json": {
              "schema": {
                "type": "string"
              }
            },
            "text/json": {
              "schema": {
                "type": "string"
              }
            },
            "application/*+json": {
              "schema": {
                "type": "string"
              }
            }
          }
        },
        "responses": {
          "200": {
            "description": "OK"
          }
        }
      },
      "delete": {
        "tags": [
          "RoleApi"
        ],
        "parameters": [
          {
            "name": "id",
            "in": "path",
            "required": true,
            "schema": {
              "type": "integer",
              "format": "int32"
            }
          }
        ],
        "responses": {
          "200": {
            "description": "OK"
          }
        }
      }
    },
    "/{id}/roles": {
      "get": {
        "tags": [
          "Utilisateur"
        ],
        "parameters": [
          {
            "name": "id",
            "in": "path",
            "required": true,
            "schema": {
              "type": "integer",
              "format": "int32"
            }
          }
        ],
        "responses": {
          "200": {
            "description": "OK"
          }
        }
      }
    },
    "/{id}/roles-v2": {
      "get": {
        "tags": [
          "Utilisateur"
        ],
        "parameters": [
          {
            "name": "id",
            "in": "path",
            "required": true,
            "schema": {
              "type": "integer",
              "format": "int32"
            }
          }
        ],
        "responses": {
          "200": {
            "description": "OK"
          }
        }
      }
    }
  },
  "components": { }
}